uzautoprom/__init__.py
uzautoprom/fmfield.py
uzautoprom/imdb.py
uzautoprom/rloader.py
uzautoprom/sfield.py
uzautoprom/abc/__init__.py
uzautoprom/abc/database.py
uzautoprom/abc/field.py
uzautoprom/abc/loader.py
uzautoprom-1.4.dist-info/LICENSE
uzautoprom-1.4.dist-info/METADATA
uzautoprom-1.4.dist-info/WHEEL
uzautoprom-1.4.dist-info/top_level.txt
uzautoprom-1.4.dist-info/RECORD
