Metadata-Version: 2.1
Name: uzautoprom
Version: 1.4
Summary: Simple contracts loader with storage and filtering functionality for official UzAuto dealers.
Home-page: https://github.com/IlhomBahoraliev/uzautoprom
Author: LidaRandom
Author-email: bahoralievdev@yandex.com
License: UNKNOWN
Platform: UNKNOWN
Classifier: Programming Language :: Python :: 3
Classifier: License :: OSI Approved :: MIT License
Classifier: Operating System :: OS Independent
Requires-Python: >=3.6
Requires-Dist: certifi (==2020.4.5.1)
Requires-Dist: chardet (==3.0.4)
Requires-Dist: idna (==2.9)
Requires-Dist: requests (==2.23.0)
